{"namedChunkGroups":{"polyfill":{"name":"polyfill","assets":[{"name":"webpack-runtime-0ad3f1f30c1de5b4777f.js","size":5102},{"name":"polyfill-5b3b90c5491b246774ef.js","size":82651}],"filteredAssets":0,"assetsSize":87753,"filteredAuxiliaryAssets":2,"auxiliaryAssetsSize":221674},"app":{"name":"app","assets":[{"name":"webpack-runtime-0ad3f1f30c1de5b4777f.js","size":5102},{"name":"styles.58ecc5651fad90675641.css","size":10953},{"name":"framework-1db9936cb2f3b196ecd7.js","size":129752},{"name":"app-903d709e96af4b5c8e76.js","size":74766}],"filteredAssets":0,"assetsSize":220573,"filteredAuxiliaryAssets":3,"auxiliaryAssetsSize":672469},"component---src-pages-404-js":{"name":"component---src-pages-404-js","assets":[{"name":"component---src-pages-404-js-572b5f3a7af5fe417de0.js","size":826}],"filteredAssets":0,"assetsSize":826,"filteredAuxiliaryAssets":1,"auxiliaryAssetsSize":1892},"component---src-pages-index-js":{"name":"component---src-pages-index-js","assets":[{"name":"styles.58ecc5651fad90675641.css","size":10953},{"name":"d0447323-5d0bad89acf1f166ec26.js","size":1181},{"name":"95b64a6e-69cae797a2c47e2e22e9.js","size":494},{"name":"1bfc9850-7a07ce1ea924cce4775b.js","size":3448},{"name":"component---src-pages-index-js-b94bd910eb0413bf3c21.js","size":28889}],"filteredAssets":0,"assetsSize":44965,"filteredAuxiliaryAssets":4,"auxiliaryAssetsSize":5808274}},"assetsByChunkName":{"polyfill":["webpack-runtime-0ad3f1f30c1de5b4777f.js","polyfill-5b3b90c5491b246774ef.js"],"app":["webpack-runtime-0ad3f1f30c1de5b4777f.js","styles.58ecc5651fad90675641.css","framework-1db9936cb2f3b196ecd7.js","app-903d709e96af4b5c8e76.js"],"component---src-pages-404-js":["component---src-pages-404-js-572b5f3a7af5fe417de0.js"],"component---src-pages-index-js":["styles.58ecc5651fad90675641.css","d0447323-5d0bad89acf1f166ec26.js","95b64a6e-69cae797a2c47e2e22e9.js","1bfc9850-7a07ce1ea924cce4775b.js","component---src-pages-index-js-b94bd910eb0413bf3c21.js"]},"childAssetsByChunkName":{}}